transformer_utils/__init__.py
transformer_utils/logit_lens/__init__.py
transformer_utils/logit_lens/hooks.py
transformer_utils/logit_lens/layer_names.py
transformer_utils/logit_lens/plotting.py
transformer_utils/low_memory/__init__.py
transformer_utils/low_memory/enable.py
transformer_utils/low_memory/load.py
transformer_utils/low_memory/load_context.py
transformer_utils/partial_forward/__init__.py
transformer_utils/util/__init__.py
transformer_utils/util/module_utils.py
transformer_utils/util/python_utils.py
transformer_utils/util/tfm_utils.py
transformer_utils-0.1.1.dist-info/LICENSE
transformer_utils-0.1.1.dist-info/METADATA
transformer_utils-0.1.1.dist-info/WHEEL
transformer_utils-0.1.1.dist-info/top_level.txt
transformer_utils-0.1.1.dist-info/RECORD
