Metadata-Version: 2.1
Name: transformer-utils
Version: 0.1.1
Summary: Large autoregressive language modeling helpers
Home-page: https://github.com/nostalgebraist/transformer-utils
Author: nostalgebraist
Author-email: nostalgebraist@gmail.com
License: MIT
Platform: UNKNOWN
License-File: LICENSE
Requires-Dist: torch
Requires-Dist: transformers
Requires-Dist: seaborn
Requires-Dist: tqdm
Requires-Dist: colorcet
